infrablocks/terraform_pkl_type_gen/__init__.py
infrablocks/terraform_pkl_type_gen/pkl_generator.py
infrablocks_terraform_pkl_type_gen-0.0.1.dist-info/LICENSE
infrablocks_terraform_pkl_type_gen-0.0.1.dist-info/LICENSE.md
infrablocks_terraform_pkl_type_gen-0.0.1.dist-info/METADATA
infrablocks_terraform_pkl_type_gen-0.0.1.dist-info/WHEEL
infrablocks_terraform_pkl_type_gen-0.0.1.dist-info/RECORD
