Metadata-Version: 2.1
Name: infrablocks.terraform_pkl_type_gen
Version: 0.0.1
Summary: Provides invoke tasks to interact with terraform
License: MIT
Author: Toby Clemson
Author-email: tobyclemson@gmail.com
Requires-Python: >=3.13,<4.0
Classifier: License :: OSI Approved :: MIT License
Classifier: Programming Language :: Python :: 3
Requires-Dist: infrablocks-invoke-factory (>=0.0.3a6,<0.0.4)
Requires-Dist: invoke (>=2.2.0,<3.0.0)
Requires-Dist: tfparse (>=0.6.16,<0.7.0)
